setup.py
pyrino/__init__.py
pyrino/_requests.py
pyrino/exceptions.py
pyrino/rubino.py
pyrino.egg-info/PKG-INFO
pyrino.egg-info/SOURCES.txt
pyrino.egg-info/dependency_links.txt
pyrino.egg-info/requires.txt
pyrino.egg-info/top_level.txt