Metadata-Version: 2.1
Name: pyrino
Version: 1.0
Summary: This is the most optimal and fastest unofficial library for rubino
Home-page: 
Author: Shayan Heidari
Author-email: snipe4kill@yahoo.com
Keywords: rubika,rubpy,rubikaio,chat,bot,robot,asyncio,rubino
Classifier: Programming Language :: Python :: 3.8
Classifier: Programming Language :: Python :: 3.9
Classifier: Programming Language :: Python :: 3.10
Classifier: Programming Language :: Python :: 3.11
Classifier: License :: OSI Approved :: MIT License
Classifier: Topic :: Internet
Classifier: Topic :: Communications
Classifier: Topic :: Communications :: Chat
Classifier: Topic :: Software Development :: Libraries
Classifier: Topic :: Software Development :: Libraries :: Python Modules
Classifier: Topic :: Software Development :: Libraries :: Application Frameworks
Requires-Python: ~=3.8
